LICENSE.md
README.md
pyproject.toml
src/blissoda/__init__.py
src/blissoda/automation.py
src/blissoda/bliss_globals.py
src/blissoda/import_utils.py
src/blissoda/processor.py
src/blissoda.egg-info/PKG-INFO
src/blissoda.egg-info/SOURCES.txt
src/blissoda.egg-info/dependency_links.txt
src/blissoda.egg-info/entry_points.txt
src/blissoda.egg-info/requires.txt
src/blissoda.egg-info/top_level.txt
src/blissoda/app/__init__.py
src/blissoda/app/__main__.py
src/blissoda/app/cli_log_utils.py
src/blissoda/app/workflow_server/__init__.py
src/blissoda/app/workflow_server/subscriberv0.py
src/blissoda/app/workflow_server/subscriberv1.py
src/blissoda/app/workflow_server/subscriberv2.py
src/blissoda/bm02/__init__.py
src/blissoda/bm02/utils.py
src/blissoda/bm02/xrpd_processor.py
src/blissoda/bm08/__init__.py
src/blissoda/bm08/converter.py
src/blissoda/bm20/__init__.py
src/blissoda/bm20/eiger2crysalis.py
src/blissoda/bm20/xrpd_processor.py
src/blissoda/bm23/__init__.py
src/blissoda/bm23/exafs_processor.py
src/blissoda/bm23/xrpd_processor.py
src/blissoda/daiquiri/__init__.py
src/blissoda/daiquiri/bliss_object.py
src/blissoda/daiquiri/mixin.py
src/blissoda/daiquiri/validators.py
src/blissoda/demo/__init__.py
src/blissoda/demo/_id31_utils.py
src/blissoda/demo/_streamline_utils.py
src/blissoda/demo/bm02.py
src/blissoda/demo/calib.py
src/blissoda/demo/example.py
src/blissoda/demo/id01.py
src/blissoda/demo/id09.py
src/blissoda/demo/id11.py
src/blissoda/demo/id22.py
src/blissoda/demo/id31.py
src/blissoda/demo/id31_streamline.py
src/blissoda/demo/id32.py
src/blissoda/demo/streamline.py
src/blissoda/demo/processors/__init__.py
src/blissoda/demo/processors/bm08.py
src/blissoda/demo/processors/ewoks_macros.py
src/blissoda/demo/processors/exafs.py
src/blissoda/demo/processors/id12.py
src/blissoda/demo/processors/id14.py
src/blissoda/demo/processors/xrpd.py
src/blissoda/demo/testing/__init__.py
src/blissoda/demo/testing/_assert.py
src/blissoda/demo/testing/_auto.py
src/blissoda/demo/testing/_celery.py
src/blissoda/demo/testing/_display.py
src/blissoda/demo/testing/_fixtures.py
src/blissoda/demo/testing/_hdf5.py
src/blissoda/demo/testing/_spec.py
src/blissoda/demo/testing/_test.py
